.travis.yml
CHANGES.rst
CONTRIBUTORS.rst
MANIFEST.in
Makefile
README.rst
bootstrap.py
buildout.cfg
setup.py
docs/LICENSE.GPL
docs/LICENSE.txt
plonesocial/__init__.py
plonesocial/__init__.pyc
plonesocial.network.egg-info/PKG-INFO
plonesocial.network.egg-info/SOURCES.txt
plonesocial.network.egg-info/dependency_links.txt
plonesocial.network.egg-info/entry_points.txt
plonesocial.network.egg-info/namespace_packages.txt
plonesocial.network.egg-info/not-zip-safe
plonesocial.network.egg-info/requires.txt
plonesocial.network.egg-info/top_level.txt
plonesocial/network/__init__.py
plonesocial/network/__init__.pyc
plonesocial/network/configure.zcml
plonesocial/network/graph.py
plonesocial/network/graph.pyc
plonesocial/network/graph.py~
plonesocial/network/interfaces.py
plonesocial/network/interfaces.pyc
plonesocial/network/interfaces.py~
plonesocial/network/monkey.py~
plonesocial/network/synci18n.sh
plonesocial/network/testing.py
plonesocial/network/testing.pyc
plonesocial/network/tool.py
plonesocial/network/tool.pyc
plonesocial/network/browser/__init__.py
plonesocial/network/browser/__init__.pyc
plonesocial/network/browser/configure.zcml
plonesocial/network/browser/configure.zcml~
plonesocial/network/browser/graph.py
plonesocial/network/browser/graph.pyc
plonesocial/network/browser/interfaces.py
plonesocial/network/browser/interfaces.pyc
plonesocial/network/browser/profile.py
plonesocial/network/browser/profile.pyc
plonesocial/network/browser/profile.py~
plonesocial/network/browser/stylesheets/plonesocial_network.css
plonesocial/network/browser/stylesheets/plonesocial_network.css~
plonesocial/network/browser/templates/graph.pt
plonesocial/network/browser/templates/maxiprofile_provider.pt
plonesocial/network/browser/templates/miniprofile_provider.pt
plonesocial/network/browser/templates/profile.pt
plonesocial/network/browser/templates/profile.pt~
plonesocial/network/locales/manual.pot
plonesocial/network/locales/plonesocial.network.pot
plonesocial/network/locales/en/LC_MESSAGES/plonesocial.network.mo
plonesocial/network/locales/en/LC_MESSAGES/plonesocial.network.po
plonesocial/network/locales/es/LC_MESSAGES/plonesocial.network.mo
plonesocial/network/locales/es/LC_MESSAGES/plonesocial.network.po
plonesocial/network/locales/nl/LC_MESSAGES/plonesocial.network.mo
plonesocial/network/locales/nl/LC_MESSAGES/plonesocial.network.po
